ticts/__init__.py
ticts/io.py
ticts/iplot.py
ticts/operation.py
ticts/pandas_mixin.py
ticts/testing.py
ticts/timeseries.py
ticts/utils.py
ticts-0.6.1.dist-info/METADATA
ticts-0.6.1.dist-info/WHEEL
ticts-0.6.1.dist-info/licenses/LICENSE
ticts-0.6.1.dist-info/RECORD
