Metadata-Version: 2.4
Name: ticts
Version: 0.6.1
Summary: A Python library for unevenly-spaced time series analysis.
Author-email: gjeusel <guillaume.jeusel@gmail.com>
License-File: LICENSE
Classifier: Intended Audience :: Developers
Classifier: Natural Language :: English
Classifier: Programming Language :: Python
Classifier: Programming Language :: Python :: 3
Classifier: Programming Language :: Python :: 3.9
Classifier: Programming Language :: Python :: 3.10
Classifier: Programming Language :: Python :: 3.11
Classifier: Topic :: Software Development
Requires-Python: >=3.9
Requires-Dist: pandas
Requires-Dist: sortedcontainers
Provides-Extra: all
Requires-Dist: bokeh; extra == 'all'
Requires-Dist: coverage==7.4.*; extra == 'all'
Requires-Dist: inline-snapshot==0.31.*; extra == 'all'
Requires-Dist: markdown-include; extra == 'all'
Requires-Dist: mdx-truly-sane-lists; extra == 'all'
Requires-Dist: mkdocs; extra == 'all'
Requires-Dist: mkdocs-exclude; extra == 'all'
Requires-Dist: mkdocs-material; extra == 'all'
Requires-Dist: mkdocstrings[python]; extra == 'all'
Requires-Dist: mypy==1.9.*; extra == 'all'
Requires-Dist: pre-commit==3.7.*; extra == 'all'
Requires-Dist: pytest-mock==3.14.*; extra == 'all'
Requires-Dist: pytest-sugar==1.0.0; extra == 'all'
Requires-Dist: pytest==8.4.*; extra == 'all'
Requires-Dist: ruff==0.4.*; extra == 'all'
Requires-Dist: types-pytz; extra == 'all'
Provides-Extra: confort
Requires-Dist: cookiecutter; extra == 'confort'
Requires-Dist: cruft; extra == 'confort'
Requires-Dist: pdbpp; extra == 'confort'
Requires-Dist: ptpython; extra == 'confort'
Requires-Dist: rich; extra == 'confort'
Provides-Extra: dev
Requires-Dist: bokeh; extra == 'dev'
Requires-Dist: coverage==7.4.*; extra == 'dev'
Requires-Dist: inline-snapshot==0.31.*; extra == 'dev'
Requires-Dist: mypy==1.9.*; extra == 'dev'
Requires-Dist: pre-commit==3.7.*; extra == 'dev'
Requires-Dist: pytest-mock==3.14.*; extra == 'dev'
Requires-Dist: pytest-sugar==1.0.0; extra == 'dev'
Requires-Dist: pytest==8.4.*; extra == 'dev'
Requires-Dist: ruff==0.4.*; extra == 'dev'
Requires-Dist: types-pytz; extra == 'dev'
Provides-Extra: doc
Requires-Dist: markdown-include; extra == 'doc'
Requires-Dist: mdx-truly-sane-lists; extra == 'doc'
Requires-Dist: mkdocs; extra == 'doc'
Requires-Dist: mkdocs-exclude; extra == 'doc'
Requires-Dist: mkdocs-material; extra == 'doc'
Requires-Dist: mkdocstrings[python]; extra == 'doc'
